[{"id":1,"first_name":"Serene","last_name":"Guierre","email":"sguierre0@theglobeandmail.com"},
{"id":2,"first_name":"Conny","last_name":"Balfre","email":"cbalfre1@bizjournals.com"},
{"id":3,"first_name":"Westbrooke","last_name":"Lascell","email":"wlascell2@ehow.com"},
{"id":4,"first_name":"Janek","last_name":"Traviss","email":"jtraviss3@ycombinator.com"},
{"id":5,"first_name":"Pattie","last_name":"Roff","email":"proff4@squidoo.com"},
{"id":6,"first_name":"Luca","last_name":"Gorvin","email":"lgorvin5@elegantthemes.com"},
{"id":7,"first_name":"Reggis","last_name":"Camble","email":"rcamble6@de.vu"},
{"id":8,"first_name":"Cosimo","last_name":"Rowly","email":"crowly7@microsoft.com"},
{"id":9,"first_name":"Jocko","last_name":"Ivanchov","email":"jivanchov8@merriam-webster.com"},
{"id":10,"first_name":"Roxanna","last_name":"McNamee","email":"rmcnamee9@cdbaby.com"},
{"id":11,"first_name":"Pierrette","last_name":"Speck","email":"pspecka@freewebs.com"},
{"id":12,"first_name":"Maddy","last_name":"Whettleton","email":"mwhettletonb@admin.ch"},
{"id":13,"first_name":"Donovan","last_name":"Dilworth","email":"ddilworthc@wikimedia.org"},
{"id":14,"first_name":"Teddi","last_name":"Corstan","email":"tcorstand@yahoo.co.jp"},
{"id":15,"first_name":"Marline","last_name":"Warnock","email":"mwarnocke@bbc.co.uk"},
{"id":16,"first_name":"Ulrica","last_name":"Deacock","email":"udeacockf@indiatimes.com"},
{"id":17,"first_name":"Geraldine","last_name":"Danser","email":"gdanserg@oaic.gov.au"},
{"id":18,"first_name":"Steffie","last_name":"Lorie","email":"slorieh@nih.gov"},
{"id":19,"first_name":"Charissa","last_name":"Ankrett","email":"cankretti@yolasite.com"},
{"id":20,"first_name":"Stephie","last_name":"Fettiplace","email":"sfettiplacej@msu.edu"},
{"id":21,"first_name":"Verney","last_name":"Trowl","email":"vtrowlk@google.com.hk"},
{"id":22,"first_name":"Carlene","last_name":"McGeever","email":"cmcgeeverl@cbslocal.com"},
{"id":23,"first_name":"Vilma","last_name":"Neno","email":"vnenom@nhs.uk"},
{"id":24,"first_name":"Mathew","last_name":"Pettengell","email":"mpettengelln@oracle.com"},
{"id":25,"first_name":"Jack","last_name":"Dumphy","email":"jdumphyo@berkeley.edu"}]